kodaksmarthome/__init__.py
kodaksmarthome/__version__.py
kodaksmarthome/api.py
kodaksmarthome/constants.py
python_kodaksmarthome-0.1.1.dist-info/LICENSE
python_kodaksmarthome-0.1.1.dist-info/METADATA
python_kodaksmarthome-0.1.1.dist-info/WHEEL
python_kodaksmarthome-0.1.1.dist-info/top_level.txt
python_kodaksmarthome-0.1.1.dist-info/RECORD
