Metadata-Version: 2.1
Name: python-kodaksmarthome
Version: 0.1.1
Summary: Python Kodak SmartHome API
Home-page: https://github.com/kairoaraujo/kodak_smarthome_api
Author: Kairo de Araujo
Author-email: kairo@dearaujo.nl
License: Apache 2.0
Project-URL: Documentation, https://python-kodaksmarthome.readthedocs.io
Project-URL: Source, https://github.com/kairoaraujo/python-kodaksmarthome
Platform: UNKNOWN
Classifier: Development Status :: 2 - Pre-Alpha
Classifier: Intended Audience :: Developers
Classifier: Natural Language :: English
Classifier: License :: OSI Approved :: Apache Software License
Classifier: Programming Language :: Python
Classifier: Programming Language :: Python :: 3.6
Classifier: Programming Language :: Python :: 3.7
Classifier: Programming Language :: Python :: 3.8
Classifier: Programming Language :: Python :: Implementation :: CPython
Classifier: Programming Language :: Python :: Implementation :: PyPy
Requires-Python: >=3.6
Requires-Dist: requests (==2.22.0)
